django_delayed_union/__init__.py
django_delayed_union/base.py
django_delayed_union/difference.py
django_delayed_union/intersection.py
django_delayed_union/union.py
django_delayed_union/utils.py
django_delayed_union-0.1.7.dist-info/AUTHORS.rst
django_delayed_union-0.1.7.dist-info/LICENSE
django_delayed_union-0.1.7.dist-info/METADATA
django_delayed_union-0.1.7.dist-info/WHEEL
django_delayed_union-0.1.7.dist-info/top_level.txt
django_delayed_union-0.1.7.dist-info/RECORD
