Metadata-Version: 2.1
Name: django-delayed-union
Version: 0.1.7
Summary: A library designed to workaround some drawbacks with Django's union, intersection, and difference operations.
Home-page: https://github.com/roverdotcom/django-delayed-union
Author: Mike Hansen
Author-email: mike@rover.com
License: BSD 3-Clause License
Platform: UNKNOWN
Classifier: Development Status :: 4 - Beta
Classifier: Intended Audience :: Developers
Classifier: License :: OSI Approved :: BSD License
Classifier: Operating System :: Unix
Classifier: Operating System :: POSIX
Classifier: Operating System :: Microsoft :: Windows
Classifier: Framework :: Django
Classifier: Framework :: Django :: 2.2
Classifier: Framework :: Django :: 3.2
Classifier: Framework :: Django :: 4.0
Classifier: Programming Language :: Python
Classifier: Programming Language :: Python :: 3
Classifier: Programming Language :: Python :: 3.7
Classifier: Programming Language :: Python :: 3.8
Classifier: Programming Language :: Python :: 3.9
Classifier: Programming Language :: Python :: 3.10
Classifier: Topic :: Utilities
Requires-Dist: django (>=2.2)
